[
  {
    "id": "842f43ca-c179-449d-a64a-e56b250d8f19",
    "email": "hans@mail.ch",
    "first": "Hans",
    "last": "Muster",
    "phone": "071 123 45 67"
  },
  {
    "id": "89f1ea45-917d-468a-8cf7-37ee4f9fb173",
    "email": "peter@mail.ch",
    "first": "Peter",
    "last": "Stein",
    "phone": "071 124 45 67"
  },
  {
    "id": "86db28e3-365e-407e-b716-549149b11a04",
    "email": "asd2@asd.ch",
    "first": "Maria",
    "last": "Muster"
  },
  {
    "id": "7cba674a-0b01-4f7d-8a1a-c56fd842fb9e",
    "email": "petra@mail.ch",
    "first": "Petra",
    "last": "Muster",
    "phone": "012 123 45 66",
    "errors": {
      "email": "email already taken"
    }
  }
]